{
  "_id": "aKTdaStpa8ugaemPs",
  "owner": {
    "username": "anon"
  },
  "createdAt": {
    "$date": 1543837072706
  },
  "modifiedAt": {
    "$date": 1543837072706
  },
  "origId": "MgC43FZpWMJiPkiAD",
  "name": "unnamed",
  "notes": "",
  "rank": 1.822967869234324,
  "private": false,
  "unlisted": false,
  "username": "-anon-",
  "avatarUrl": "",
  "settings": {
    "num": 3,
    "mode": "POINTS",
    "sound": "https://soundcloud.com/caseandpoint/case-point-upgrade-free-download",
    "lineSize": "NATIVE",
    "backgroundColor": [
      0,
      0,
      0,
      1
    ],
    "shader": "void main() {\n  gl_PointSize = 10.0;\n  gl_Position = vec4(0, 0, 0, 1);\n  v_color = vec4(1, 0, 0, 1);\n}"
  },
  "screenshotURL": "data/images/images-n9t2z0wfs6yojrtp6-thumbnail.jpg",
  "hasSound": true,
  "views": 21,
  "likes": 0,
  "revisionId": "Tgp7asDYtdEFCfoiP"
}