{
  "_id": "sYdAq9WutD8TN6uxp",
  "owner": {
    "username": "anon"
  },
  "createdAt": {
    "$date": 1634503353770
  },
  "modifiedAt": {
    "$date": 1634503353770
  },
  "origId": null,
  "name": "first test",
  "notes": "",
  "rank": 1.6999655871075299,
  "private": false,
  "unlisted": false,
  "username": "-anon-",
  "avatarUrl": "",
  "settings": {
    "num": 1360,
    "mode": "POINTS",
    "sound": "",
    "lineSize": "NATIVE",
    "backgroundColor": [
      0,
      0,
      0,
      1
    ],
    "shader": "void main() {\n  \n  float down = floor(sqrt(vertexCount));\n  float across = floor(vertexCount / down);\n  \n  // float pointSize = 5.;\n  \n  float x = mod(vertexId, across);\n  float y = floor(vertexId /across);\n  \n  float u = x/(across-1.);\n  float v = y/(across-1.);\n  \n  float ux = u * 2. - 1.;\n  float vy = v * 2. - 1.;\n\n  \n  gl_Position = vec4(ux,vy,0,1);\n  gl_PointSize = 10.;\n  gl_PointSize *= 20. / across;\n  gl_PointSize *= resolution.x / 600.;\n  \n  v_color = vec4(1,0,0,1);\n \n}"
  },
  "screenshotURL": "data/images/images-vucna6khkfe36l2eh-thumbnail.jpg",
  "hasSound": "",
  "views": 63,
  "likes": 0,
  "revisionId": "WnpJksv7RZcv5Ez4L"
}