{
  "_id": "svRerLfafn3PP5Jif",
  "owner": {
    "_id": "EwBjpT9SHvAcQtLHx",
    "createdAt": {
      "$date": "1565652027829"
    },
    "username": "seb0fh",
    "profile": {
      "avatarUrl": "https://secure.gravatar.com/avatar/952c6ff0f2b9ef4d12f4664071f72153?default=retro&size=200"
    }
  },
  "createdAt": {
    "$date": "1565652036499"
  },
  "modifiedAt": {
    "$date": "1565652234438"
  },
  "origId": null,
  "name": "spiral sphere",
  "notes": "",
  "rank": "1.5448916684368619",
  "private": false,
  "unlisted": true,
  "username": "seb0fh",
  "avatarUrl": "https://secure.gravatar.com/avatar/952c6ff0f2b9ef4d12f4664071f72153?default=retro&size=200",
  "settings": {
    "num": 1838,
    "mode": "TRI_STRIP",
    "sound": "https://soundcloud.com/sebchevrel/ninetyseven",
    "lineSize": "NATIVE",
    "backgroundColor": [
      0,
      0,
      0,
      1
    ],
    "shader": "#define PI radians(180.0)\n\nvec3 hsv2rgb(vec3 c) {\n  c = vec3(c.x, clamp(c.yz, 0.0, 1.0));\n  vec4 K = vec4(1.0, 2.0 / 3.0, 1.0 / 3.0, 3.0);\n  vec3 p = abs(fract(c.xxx + K.xyz) * 6.0 - K.www);\n  return c.z * mix(K.xxx, clamp(p - K.xxx, 0.0, 1.0), c.y);\n}\n\nmat4 rotX(float angleInRadians) {\n    float s = sin(angleInRadians);\n    float c = cos(angleInRadians);\n  \t\n    return mat4( \n      1, 0, 0, 0,\n      0, c, s, 0,\n      0, -s, c, 0,\n      0, 0, 0, 1);  \n}\n\nmat4 rotY(float angleInRadians) {\n    float s = sin(angleInRadians);\n    float c = cos(angleInRadians);\n  \t\n    return mat4( \n      c, 0,-s, 0,\n      0, 1, 0, 0,\n      s, 0, c, 0,\n      0, 0, 0, 1);  \n}\n\nmat4 rotZ(float angleInRadians) {\n    float s = sin(angleInRadians);\n    float c = cos(angleInRadians);\n  \t\n    return mat4( \n      c,-s, 0, 0, \n      s, c, 0, 0,\n      0, 0, 1, 0,\n      0, 0, 0, 1); \n}\n\nmat4 trans(vec3 trans) {\n  return mat4(\n    1, 0, 0, 0,\n    0, 1, 0, 0,\n    0, 0, 1, 0,\n    trans, 1);\n}\n\nmat4 ident() {\n  return mat4(\n    1, 0, 0, 0,\n    0, 1, 0, 0,\n    0, 0, 1, 0,\n    0, 0, 0, 1);\n}\n\nmat4 scale(vec3 s) {\n  return mat4(\n    s[0], 0, 0, 0,\n    0, s[1], 0, 0,\n    0, 0, s[2], 0,\n    0, 0, 0, 1);\n}\n\nmat4 uniformScale(float s) {\n  return mat4(\n    s, 0, 0, 0,\n    0, s, 0, 0,\n    0, 0, s, 0,\n    0, 0, 0, 1);\n}\n\nmat4 persp(float fov, float aspect, float zNear, float zFar) {\n  float f = tan(PI * 0.5 - 0.5 * fov);\n  float rangeInv = 1.0 / (zNear - zFar);\n\n  return mat4(\n    f / aspect, 0, 0, 0,\n    0, f, 0, 0,\n    0, 0, (zNear + zFar) * rangeInv, -1,\n    0, 0, zNear * zFar * rangeInv * 2., 0);\n}\n\nmat4 trInv(mat4 m) {\n  mat3 i = mat3(\n    m[0][0], m[1][0], m[2][0], \n    m[0][1], m[1][1], m[2][1], \n    m[0][2], m[1][2], m[2][2]);\n  vec3 t = -i * m[3].xyz;\n    \n  return mat4(\n    i[0], t[0], \n    i[1], t[1],\n    i[2], t[2],\n    0, 0, 0, 1);\n}\n\nmat4 transpose(mat4 m) {\n  return mat4(\n    m[0][0], m[1][0], m[2][0], m[3][0], \n    m[0][1], m[1][1], m[2][1], m[3][1],\n    m[0][2], m[1][2], m[2][2], m[3][2],\n    m[0][3], m[1][3], m[2][3], m[3][3]);\n}\n\nmat4 lookAt(vec3 eye, vec3 target, vec3 up) {\n  vec3 zAxis = normalize(eye - target);\n  vec3 xAxis = normalize(cross(up, zAxis));\n  vec3 yAxis = cross(zAxis, xAxis);\n\n  return mat4(\n    xAxis, 0,\n    yAxis, 0,\n    zAxis, 0,\n    eye, 1);\n}\n\nmat4 inverse(mat4 m) {\n  float\n      a00 = m[0][0], a01 = m[0][1], a02 = m[0][2], a03 = m[0][3],\n      a10 = m[1][0], a11 = m[1][1], a12 = m[1][2], a13 = m[1][3],\n      a20 = m[2][0], a21 = m[2][1], a22 = m[2][2], a23 = m[2][3],\n      a30 = m[3][0], a31 = m[3][1], a32 = m[3][2], a33 = m[3][3],\n\n      b00 = a00 * a11 - a01 * a10,\n      b01 = a00 * a12 - a02 * a10,\n      b02 = a00 * a13 - a03 * a10,\n      b03 = a01 * a12 - a02 * a11,\n      b04 = a01 * a13 - a03 * a11,\n      b05 = a02 * a13 - a03 * a12,\n      b06 = a20 * a31 - a21 * a30,\n      b07 = a20 * a32 - a22 * a30,\n      b08 = a20 * a33 - a23 * a30,\n      b09 = a21 * a32 - a22 * a31,\n      b10 = a21 * a33 - a23 * a31,\n      b11 = a22 * a33 - a23 * a32,\n\n      det = b00 * b11 - b01 * b10 + b02 * b09 + b03 * b08 - b04 * b07 + b05 * b06;\n\n  return mat4(\n      a11 * b11 - a12 * b10 + a13 * b09,\n      a02 * b10 - a01 * b11 - a03 * b09,\n      a31 * b05 - a32 * b04 + a33 * b03,\n      a22 * b04 - a21 * b05 - a23 * b03,\n      a12 * b08 - a10 * b11 - a13 * b07,\n      a00 * b11 - a02 * b08 + a03 * b07,\n      a32 * b02 - a30 * b05 - a33 * b01,\n      a20 * b05 - a22 * b02 + a23 * b01,\n      a10 * b10 - a11 * b08 + a13 * b06,\n      a01 * b08 - a00 * b10 - a03 * b06,\n      a30 * b04 - a31 * b02 + a33 * b00,\n      a21 * b02 - a20 * b04 - a23 * b00,\n      a11 * b07 - a10 * b09 - a12 * b06,\n      a00 * b09 - a01 * b07 + a02 * b06,\n      a31 * b01 - a30 * b03 - a32 * b00,\n      a20 * b03 - a21 * b01 + a22 * b00) / det;\n}\n\nmat4 cameraLookAt(vec3 eye, vec3 target, vec3 up) {\n  #if 1\n  return inverse(lookAt(eye, target, up));\n  #else\n  vec3 zAxis = normalize(target - eye);\n  vec3 xAxis = normalize(cross(up, zAxis));\n  vec3 yAxis = cross(zAxis, xAxis);\n\n  return mat4(\n    xAxis, 0,\n    yAxis, 0,\n    zAxis, 0,\n    -dot(xAxis, eye), -dot(yAxis, eye), -dot(zAxis, eye), 1);  \n  #endif\n  \n}\n\n\n\n\nvoid main()\n{  \n   float numTurns = vertexCount/128.0;\n  float u = floor(vertexId/2.0) / (vertexCount/2.0);\n  float v = mod(vertexId,2.0);\n        \n  float snd = texture2D(volume, vec2(0.0,u*0.25)).a;\n  float snd2 = texture2D(volume, vec2(0.0,u*0.0625)).a;\n  \n  float lon = u * PI*2.0*numTurns;                    \n  float lat = u * PI - PI*0.5 + v*PI/numTurns*(snd*0.9+0.1);\n        \n  float h = sin(lat);\n  float rad = sqrt(1.0 - h * h) + snd2*0.5;\n\n  vec3 nor = vec3(cos(lon)*rad, h , sin(lon)*rad);\n  \n  \n  \n  mat4 VP = persp(PI*0.25, resolution.x/resolution.y, 0.1, 10000.0) * cameraLookAt(vec3(0.0,1.0,5.0),vec3(0.0),vec3(0.0,1.0,0.0));\n                                                                                   \n  gl_Position = VP * vec4(nor,1.0);\n  v_color = vec4(nor*0.5 + 0.5,1.0);\n  \n}"
  },
  "screenshotURL": "data/images/images-jvy1otr1kog86tcd8-thumbnail.jpg",
  "hasSound": true,
  "views": "10",
  "likes": "0",
  "revisionId": "2qJTutE9uRdvfnbQ3"
}